LICENSE
MANIFEST.in
nyx.1
run_nyx
run_tests.py
setup.py
nyx/__init__.py
nyx/arguments.py
nyx/curses.py
nyx/log.py
nyx/menu.py
nyx/popups.py
nyx/starter.py
nyx/tracker.py
nyx.egg-info/PKG-INFO
nyx.egg-info/SOURCES.txt
nyx.egg-info/dependency_links.txt
nyx.egg-info/entry_points.txt
nyx.egg-info/requires.txt
nyx.egg-info/top_level.txt
nyx/panel/__init__.py
nyx/panel/config.py
nyx/panel/connection.py
nyx/panel/graph.py
nyx/panel/header.py
nyx/panel/interpreter.py
nyx/panel/log.py
nyx/panel/torrc.py
nyx/settings/attributes.cfg
nyx/settings/dedup.cfg
test/__init__.py
test/arguments.py
test/cache.py
test/installation.py
test/menu.py
test/popups.py
test/settings.cfg
test/subwindow.py
test/log/__init__.py
test/log/condense_runlevels.py
test/log/log_entry.py
test/log/log_group.py
test/log/read_tor_log.py
test/log/data/daybreak_deduplication
test/log/data/empty_file
test/log/data/malformed_date
test/log/data/malformed_line
test/log/data/malformed_runlevel
test/log/data/multiple_tor_instances
test/log/data/tor_log
test/panel/__init__.py
test/panel/config.py
test/panel/connection.py
test/panel/graph.py
test/panel/header.py
test/panel/interpreter.py
test/panel/log.py
test/panel/torrc.py
test/tracker/__init__.py
test/tracker/connection_tracker.py
test/tracker/daemon.py
test/tracker/port_usage_tracker.py
test/tracker/resource_tracker.py
web/HFM_INT_0001.mp3
web/index.html
web/jquery.tools.min.js
web/nyxrc.sample
web/styles.css
web/styles_no_js.css
web/changelog/index.html
web/changelog/legacy.html
web/images/bugtracker.png
web/images/down_arrow_brown.png
web/images/down_arrow_white.png
web/images/email.png
web/images/favicon.png
web/images/grid.png
web/images/irc.png
web/images/irc.xcf
web/images/logo.png
web/images/logo.svg
web/images/source.txt
web/images/download/archlinux.png
web/images/download/debian.png
web/images/download/fedora.png
web/images/download/freebsd.png
web/images/download/gentoo.png
web/images/download/git.png
web/images/download/git_alt.png
web/images/download/netbsd.png
web/images/download/openbsd.png
web/images/download/osx.png
web/images/download/pypi.png
web/images/download/redhat.png
