Metadata-Version: 1.1
Name: nyx
Version: 2.1.0
Summary: Terminal status monitor for Tor (https://www.torproject.org/).
Home-page: https://nyx.torproject.org/
Author: Damian Johnson
Author-email: atagar@torproject.org
License: GPLv3
Keywords: tor onion controller
Platform: UNKNOWN
Classifier: Development Status :: 5 - Production/Stable
Classifier: Environment :: Console :: Curses
Classifier: Intended Audience :: System Administrators
Classifier: License :: OSI Approved :: GNU General Public License v3 (GPLv3)
Classifier: Topic :: Security
